<?xml version="1.0" encoding="UTF-8"?>
<vosi:capabilities
    xmlns:vosi="http://www.ivoa.net/xml/VOSICapabilities/v1.0"
    xmlns:xsi="http://www.w3.org/2001/XMLSchema-instance"
    xmlns:vs="http://www.ivoa.net/xml/VODataService/v1.1">

  <capability standardID="vos://cadc.nrc.ca~vospace/CADC/std/inventory/#TBD-1.0">
    <interface xsi:type="vs:ParamHTTP" role="std">
      <accessURL use="base">http://replace.com/TBD/TBD</accessURL>
      <securityMethod />
      <securityMethod standardID="ivo://ivoa.net/sso#cookie" />
      <securityMethod standardID="ivo://ivoa.net/sso#tls-with-certificate" />
      <securityMethod standardID="vos://cadc.nrc.ca~vospace/CADC/std/Auth#token-1.0"/>    
    </interface>
  </capability>

  <capability standardID="ivo://ivoa.net/std/VOSI#capabilities">
    <interface xsi:type="vs:ParamHTTP" role="std">
      <accessURL use="full">https://replace.com/TBD/capabilities</accessURL>
    </interface>
  </capability>

  <capability standardID="ivo://ivoa.net/std/VOSI#availability">
    <interface xsi:type="vs:ParamHTTP" role="std">
      <accessURL use="full">https://replace.com/TBD/availability</accessURL>
    </interface>
  </capability>
  
  <capability standardID="vos://cadc.nrc.ca~vospace/CADC/std/LOGGING#logControl-1.0">
    <interface xsi:type="vs:ParamHTTP" role="std" version="1.0">
      <accessURL use="full">https://replace.com/TBD/logControl</accessURL>
      <securityMethod standardID="ivo://ivoa.net/sso#tls-with-certificate" />
    </interface>
  </capability>
  
</vosi:capabilities>

